rivuletpy/__init__.py
rivuletpy/msfm/_msfm.c
rivuletpy/msfm/_msfm.h
rivuletpy/msfm/common.c
rivuletpy/msfm/msfmmodule.c
rivuletpy/soma.py
rivuletpy/swc.py
rivuletpy/trace.py
rivuletpy/utils/__init__.py
rivuletpy/utils/io.py
rivuletpy/utils/metrics.py
rivuletpy/utils/rendering.py
rivuletpy/utils/rendering3.py
msfm.cpython-38-x86_64-linux-gnu.so
rivuletpy-0.3.0.dist-info/LICENSE.txt
rivuletpy-0.3.0.dist-info/WHEEL
rivuletpy-0.3.0.dist-info/METADATA
rivuletpy-0.3.0.dist-info/RECORD
