Metadata-Version: 2.1
Name: rivuletpy
Version: 0.3.0
Summary: Rivuletpy: a powerful tool to automatically trace single neurons from 3D light microscopic images.
License: BSD
Author: RivuletStudio
Requires-Python: >=3.8,<3.11
Classifier: License :: Other/Proprietary License
Classifier: Programming Language :: Python :: 3
Classifier: Programming Language :: Python :: 3.8
Classifier: Programming Language :: Python :: 3.9
Classifier: Programming Language :: Python :: 3.10
Requires-Dist: Cython (>=0.29.32,<0.30.0)
Requires-Dist: matplotlib (>=3.6.0,<4.0.0)
Requires-Dist: nibabel (>=4.0.2,<5.0.0)
Requires-Dist: numpy (>=1.23.3,<2.0.0)
Requires-Dist: pyglet (>=1.5.27,<2.0.0)
Requires-Dist: pylibtiff (>=0.4.4,<0.5.0)
Requires-Dist: scikit-fmm (>=2022.8.15,<2023.0.0)
Requires-Dist: scikit-image (>=0.18,<0.19)
Requires-Dist: scipy (>=1.9.1,<2.0.0)
Requires-Dist: tqdm (>=4.64.1,<5.0.0)
